MANIFEST.in
README.rst
setup.py
azkaban_orchestrator/__init__.py
azkaban_orchestrator/azkaban.py
azkaban_orchestrator/diagram.py
azkaban_orchestrator/graph.py
azkaban_orchestrator/orchestrator.py
azkaban_orchestrator.egg-info/PKG-INFO
azkaban_orchestrator.egg-info/SOURCES.txt
azkaban_orchestrator.egg-info/dependency_links.txt
azkaban_orchestrator.egg-info/requires.txt
azkaban_orchestrator.egg-info/top_level.txt