Metadata-Version: 1.0
Name: azkaban-orchestrator
Version: 0.0.1
Summary: Azkaban Orchestrator
Home-page: https://github.com/telegraph/azkaban-orchestrator
Author: Telegraph Data Platform team
Author-email: UNKNOWN
License: MIT
Platform: UNKNOWN
